{"responses":{"200":{"description":"Bulk remediation results","content":{"application/json":{"schema":{"type":"object","description":"Response for bulk remediation.","required":["succeeded","failed","errors"],"properties":{"errors":{"type":"array","items":{"type":"object","description":"Individual error in bulk remediation.","required":["detection_id","error"],"properties":{"detection_id":{"type":"string","format":"uuid","description":"Detection ID that failed."},"error":{"type":"string","description":"Error message."}},"title":"BulkRemediationError"},"description":"Details of failures."},"failed":{"type":"integer","format":"int64","description":"Number of failed remediations."},"succeeded":{"type":"integer","format":"int64","description":"Number of successful remediations."}},"title":"BulkRemediateResponse"}}}},"400":{"description":"Invalid request"},"401":{"description":"Unauthorized"},"500":{"description":"Internal server error"}}}