{"responses":{"200":{"description":"Tool invocation result","content":{"application/json":{"schema":{"type":"object","description":"Response for successful tool invocation.","required":["call_id","result","latency_ms"],"properties":{"call_id":{"type":"string","format":"uuid","description":"Unique identifier for this tool call (for audit)."},"latency_ms":{"type":"number","format":"double","description":"Execution latency in milliseconds."},"result":{"description":"Tool execution result."}},"title":"McpCallResponse"}}}},"400":{"description":"Invalid parameters"},"403":{"description":"Agent not authorized"},"404":{"description":"Tool not found"},"429":{"description":"Rate limit exceeded"}}}