{"title":"Body","body":{"content":{"application/json":{"schema":{"type":"object","description":"Request to create a new `SoD` exemption.","required":["rule_id","user_id","justification","expires_at"],"properties":{"expires_at":{"type":"string","format":"date-time","description":"When the exemption expires."},"justification":{"type":"string","description":"Business justification (required)."},"rule_id":{"type":"string","format":"uuid","description":"Rule to exempt."},"user_id":{"type":"string","format":"uuid","description":"User to exempt."}},"title":"CreateSodExemptionRequest"}}},"required":true}}