{"title":"Body","body":{"content":{"application/json":{"schema":{"type":"object","description":"Request to execute a merge operation.","required":["source_identity_id","target_identity_id","entitlement_strategy"],"properties":{"attribute_selections":{"nullable":true},"entitlement_selections":{"type":"array","items":{"type":"string","format":"uuid"},"nullable":true},"entitlement_strategy":{"type":"string","description":"Entitlement consolidation strategy.","enum":["union","intersection","manual"],"title":"GovEntitlementStrategy"},"sod_override_reason":{"type":"string","nullable":true},"source_identity_id":{"type":"string","format":"uuid"},"target_identity_id":{"type":"string","format":"uuid"}},"title":"MergeExecuteRequest"}}},"required":true}}