{"parameters":[{"name":"simulation_id","in":"path","description":"Simulation ID","required":true,"schema":{"type":"string","format":"uuid"}},{"name":"user_id","in":"query","description":"Filter by user ID.","required":false,"schema":{"type":"string","format":"uuid","nullable":true}},{"name":"has_warnings","in":"query","description":"Filter by whether result has warnings.","required":false,"schema":{"type":"boolean","nullable":true}},{"name":"offset","in":"query","description":"Page offset (default: 0).","required":false,"schema":{"type":"integer","format":"int64","nullable":true}},{"name":"limit","in":"query","description":"Page size (default: 20, max: 100).","required":false,"schema":{"type":"integer","format":"int64","nullable":true}}]}