{"parameters":[{"name":"user_id","in":"query","required":false,"schema":{"type":"string","format":"uuid","nullable":true}},{"name":"template_id","in":"query","required":false,"schema":{"type":"string","format":"uuid","nullable":true}},{"name":"include_expired","in":"query","required":false,"schema":{"type":"boolean"}},{"name":"include_revoked","in":"query","required":false,"schema":{"type":"boolean"}},{"name":"cursor","in":"query","required":false,"schema":{"type":"string","format":"date-time","nullable":true}},{"name":"limit","in":"query","required":false,"schema":{"type":"integer","format":"int32"}}]}