{"responses":{"200":{"description":"List of templates","content":{"application/json":{"schema":{"type":"array","items":{"type":"object","description":"Summary of an email template.","required":["template_type","locale","is_customized","is_active"],"properties":{"is_active":{"type":"boolean"},"is_customized":{"type":"boolean"},"locale":{"type":"string"},"template_type":{"type":"string"},"updated_at":{"type":"string","format":"date-time","nullable":true}},"title":"EmailTemplateSummaryResponse"}}}}},"401":{"description":"Not authenticated"},"403":{"description":"Not authorized"}}}