{"parameters":[{"name":"status","in":"query","description":"Filter by status","required":false,"schema":{"type":"array","items":{"type":"string"},"nullable":true}},{"name":"application_id","in":"query","description":"Filter by application","required":false,"schema":{"type":"string","format":"uuid","nullable":true}},{"name":"user_id","in":"query","description":"Filter by target user","required":false,"schema":{"type":"string","format":"uuid","nullable":true}},{"name":"sla_breached","in":"query","description":"Filter by SLA breach status","required":false,"schema":{"type":"boolean","nullable":true}},{"name":"assignee_id","in":"query","description":"Filter by assignee","required":false,"schema":{"type":"string","format":"uuid","nullable":true}},{"name":"limit","in":"query","description":"Maximum results to return","required":false,"schema":{"type":"integer","format":"int64","nullable":true}},{"name":"offset","in":"query","description":"Results to skip","required":false,"schema":{"type":"integer","format":"int64","nullable":true}}]}