{"responses":{"200":{"description":"List of pending approvals","content":{"application/json":{"schema":{"type":"object","description":"Paginated list of pending approvals.","required":["items","total","limit","offset"],"properties":{"items":{"type":"array","items":{"type":"object","description":"A pending approval item.","required":["request_id","requester_id","entitlement_id","entitlement_name","justification","current_step","total_steps","has_sod_warning","is_delegate","submitted_at"],"properties":{"current_step":{"type":"integer","format":"int32","description":"Current step in the workflow."},"delegator_id":{"type":"string","format":"uuid","description":"Original approver (if delegated).","nullable":true},"entitlement_id":{"type":"string","format":"uuid","description":"Entitlement ID."},"entitlement_name":{"type":"string","description":"Entitlement name."},"has_sod_warning":{"type":"boolean","description":"Whether `SoD` violations were detected."},"is_delegate":{"type":"boolean","description":"Whether this is a delegated approval."},"justification":{"type":"string","description":"Business justification."},"previous_decisions":{"type":"array","items":{"type":"object","description":"Summary of a previous decision.","required":["step_order","decision","approver_id","decided_at"],"properties":{"approver_id":{"type":"string","format":"uuid","description":"Approver ID."},"approver_name":{"type":"string","description":"Approver name.","nullable":true},"comments":{"type":"string","description":"Comments.","nullable":true},"decided_at":{"type":"string","format":"date-time","description":"When the decision was made."},"decision":{"type":"string","description":"Decision types for approvals.","enum":["approved","rejected"],"title":"GovDecisionType"},"step_order":{"type":"integer","format":"int32","description":"Step this decision was for."}},"title":"DecisionSummary"},"description":"Previous decisions in this request."},"request_id":{"type":"string","format":"uuid","description":"Access request ID."},"requester_id":{"type":"string","format":"uuid","description":"Requester user ID."},"requester_name":{"type":"string","description":"Requester display name (if available).","nullable":true},"sod_warnings":{"type":"array","items":{"type":"object","description":"Schema for SodWarningSummary","title":"SodWarningSummary"},"description":"`SoD` violation summaries.","nullable":true},"submitted_at":{"type":"string","format":"date-time","description":"When the request was submitted."},"total_steps":{"type":"integer","format":"int32","description":"Total steps in the workflow."}},"title":"PendingApprovalItem"},"description":"List of pending approval items."},"limit":{"type":"integer","format":"int64","description":"Limit used for query."},"offset":{"type":"integer","format":"int64","description":"Offset used for query."},"total":{"type":"integer","format":"int64","description":"Total count."}},"title":"PendingApprovalListResponse"}}}},"401":{"description":"Unauthorized"},"500":{"description":"Internal server error"}}}