{"title":"Body","body":{"content":{"application/json":{"schema":{"type":"object","description":"Request to simulate meta-role changes.","required":["simulation_type"],"properties":{"criteria_changes":{"type":"array","items":{"type":"object","description":"Request to create a meta-role criterion.","required":["field","operator","value"],"properties":{"field":{"type":"string","description":"Field to match against (`risk_level`, `application_id`, `owner_id`, status, `is_delegable`, metadata)."},"operator":{"type":"string","description":"Operator for criteria comparison.","enum":["eq","neq","in","not_in","gt","gte","lt","lte","contains","starts_with"],"title":"CriteriaOperator"},"value":{"description":"Value to compare against (JSON format for flexibility)."}},"title":"CreateMetaRoleCriteriaRequest"},"description":"Updated criteria (for criteria change simulations).","nullable":true},"limit":{"type":"integer","format":"int64","description":"Limit results (default: 100)."},"meta_role_data":{"allOf":[{"type":"object","description":"Request to create a new meta-role.","required":["name","criteria"],"properties":{"constraints":{"type":"array","items":{"type":"object","description":"Request to add a constraint to a meta-role.","required":["constraint_type","constraint_value"],"properties":{"constraint_type":{"type":"string","description":"Constraint type (`max_session_duration`, `require_mfa`, `ip_whitelist`, `approval_required`)."},"constraint_value":{"description":"Constraint configuration (JSON format)."}},"title":"CreateMetaRoleConstraintRequest"},"description":"Constraints to inherit (optional).","nullable":true},"criteria":{"type":"array","items":{"type":"object","description":"Request to create a meta-role criterion.","required":["field","operator","value"],"properties":{"field":{"type":"string","description":"Field to match against (`risk_level`, `application_id`, `owner_id`, status, `is_delegable`, metadata)."},"operator":{"type":"string","description":"Operator for criteria comparison.","enum":["eq","neq","in","not_in","gt","gte","lt","lte","contains","starts_with"],"title":"CriteriaOperator"},"value":{"description":"Value to compare against (JSON format for flexibility)."}},"title":"CreateMetaRoleCriteriaRequest"},"description":"Matching criteria for this meta-role."},"criteria_logic":{"type":"string","description":"Criteria logic for combining multiple conditions.","enum":["and","or"],"title":"CriteriaLogic"},"description":{"type":"string","description":"Description of the meta-role (max 2000 characters).","nullable":true},"entitlements":{"type":"array","items":{"type":"object","description":"Request to add an entitlement to a meta-role.","required":["entitlement_id"],"properties":{"entitlement_id":{"type":"string","format":"uuid","description":"The entitlement ID to inherit."},"permission_type":{"allOf":[{"type":"string","description":"Permission type for inherited entitlements.","enum":["grant","deny"],"title":"PermissionType"}],"nullable":true}},"title":"CreateMetaRoleEntitlementRequest"},"description":"Entitlements to inherit (optional).","nullable":true},"name":{"type":"string","description":"Display name for the meta-role (1-255 characters)."},"priority":{"type":"integer","format":"int32","description":"Priority for conflict resolution (lower = higher priority, default: 100)."}},"title":"CreateMetaRoleRequest"}],"nullable":true},"meta_role_id":{"type":"string","format":"uuid","description":"Meta-role ID (for update/delete simulations).","nullable":true},"simulation_type":{"type":"string","description":"Type of meta-role simulation.","enum":["create","update","delete","criteria_change","enable","disable"],"title":"MetaRoleSimulationType"}},"title":"SimulateMetaRoleRequest"}}},"required":true}}